ul_py_tool/__init__.py
ul_py_tool/main.py
ul_py_tool/py.typed
ul_py_tool/__tests__/__init__.py
ul_py_tool/__tests__/conftest.py
ul_py_tool/commands/__init__.py
ul_py_tool/commands/cmd.py
ul_py_tool/commands/cmd_build_images.py
ul_py_tool/commands/cmd_cleanup.py
ul_py_tool/commands/cmd_clone_components.py
ul_py_tool/commands/cmd_fix_own.py
ul_py_tool/commands/cmd_fmt.py
ul_py_tool/commands/cmd_install.py
ul_py_tool/commands/cmd_lint.py
ul_py_tool/commands/cmd_release.py
ul_py_tool/commands/cmd_release_dcf.py
ul_py_tool/commands/cmd_release_dcf_dev.py
ul_py_tool/commands/cmd_render_values.py
ul_py_tool/commands/cmd_service_version.py
ul_py_tool/commands/cmd_stats.py
ul_py_tool/commands/cmd_test.py
ul_py_tool/commands/cmd_test_secrets.py
ul_py_tool/commands/cmd_version.py
ul_py_tool/commands/cmp_outdated.py
ul_py_tool/commands/conf.py
ul_py_tool/conf/editorconfig
ul_py_tool/conf/git.hook.pre-commit.sh
ul_py_tool/conf/git.hook.pre-push.sh
ul_py_tool/conf/gitattributes
ul_py_tool/conf/gitignore
ul_py_tool/conf/isort.cfg
ul_py_tool/conf/mypy.ini
ul_py_tool/conf/pytest.ini
ul_py_tool/conf/python-version
ul_py_tool/conf/yamlint.yml
ul_py_tool/utils/__init__.py
ul_py_tool/utils/arg_file_exists.py
ul_py_tool/utils/arg_files_glob.py
ul_py_tool/utils/arg_str2bool.py
ul_py_tool/utils/arg_str2list.py
ul_py_tool/utils/arg_str2yaml.py
ul_py_tool/utils/aseembly.py
ul_py_tool/utils/class_property.py
ul_py_tool/utils/colors.py
ul_py_tool/utils/docker_compose.py
ul_py_tool/utils/docker_file.py
ul_py_tool/utils/fs.py
ul_py_tool/utils/input_lines.py
ul_py_tool/utils/pipfile.py
ul_py_tool/utils/run_command.py
ul_py_tool/utils/semver.py
ul_py_tool/utils/step.py
ul_py_tool/utils/write_stdout.py
ul_py_tool/utils/__tests__/__init__.py
ul_py_tool/utils/__tests__/pipfile.py
ul_py_tool-2.2.5.dist-info/METADATA
ul_py_tool-2.2.5.dist-info/WHEEL
ul_py_tool-2.2.5.dist-info/entry_points.txt
ul_py_tool-2.2.5.dist-info/top_level.txt
ul_py_tool-2.2.5.dist-info/RECORD
